<?xml version="1.0" encoding="UTF-8" standalone="yes"?>
<contentHaul xmlns:a="http://www.appian.com/ae/types/2009">
    <versionUuid>_a-0000e48b-4cb4-8000-9baf-011c48011c48_3412477</versionUuid>
    <rulesFolder>
        <name>SS Utility Rules</name>
        <uuid>d89db7b5-69bd-4979-875f-e27f1349d7dc</uuid>
        <description>Folder containing all utility rules for data manipulation in the Sandbox- Sim application [Base]</description>
        <parentUuid>875169c8-ef1e-4b3b-b45d-4f11438a0e86</parentUuid>
        <visibility>
            <advertise>false</advertise>
            <hierarchy>true</hierarchy>
            <indexable>true</indexable>
            <quota>false</quota>
            <searchable>true</searchable>
            <system>false</system>
            <unlogged>false</unlogged>
        </visibility>
    </rulesFolder>
    <roleMap public="true">
        <role inherit="true" allowForAll="false" name="readers">
            <users/>
            <groups/>
        </role>
        <role inherit="true" allowForAll="false" name="authors">
            <users/>
            <groups/>
        </role>
        <role inherit="true" allowForAll="false" name="administrators">
            <users/>
            <groups/>
        </role>
        <role inherit="false" allowForAll="false" name="denyReaders">
            <users/>
            <groups/>
        </role>
        <role inherit="false" allowForAll="false" name="denyAuthors">
            <users/>
            <groups/>
        </role>
        <role inherit="false" allowForAll="false" name="denyAdministrators">
            <users/>
            <groups/>
        </role>
    </roleMap>
    <history>
        <historyInfo versionUuid="_a-0000e48b-4cb4-8000-9baf-011c48011c48_3412477"/>
    </history>
</contentHaul>
